[
  {
    "name": "Wispr Flow",
    "website": "https://wisprflow.ai/",
    "description": "AI dictation product that converts speech into polished text across Mac, Windows, iPhone, and newly launched Android.",
    "why_matters": "Launched Android on Feb 23, 2026 and claims 4x typing speed (220 vs 45 wpm), signaling strong cross-platform voice productivity demand.",
    "dark_horse_index": 3,
    "source_url": "https://techcrunch.com/2026/02/23/wispr-flow-launches-an-android-app-for-ai-powered-dictation/",
    "source": "TechCrunch + Product Hunt",
    "discovered_at": "2026-02-25T02:57:44.139635+00:00",
    "categories": [
      "Productivity",
      "Voice AI"
    ],
    "region": "US"
  },
  {
    "name": "Callio",
    "website": "https://www.callio.dev/",
    "description": "API gateway and marketplace that lets AI agents discover and execute multiple third-party APIs through one endpoint.",
    "why_matters": "Listed on Feb 23 Product Hunt and advertises 50+ APIs with one key and sub-2-minute setup, reducing integration overhead for agent builders.",
    "dark_horse_index": 4,
    "source_url": "https://www.producthunt.com/leaderboard/daily/2026/2/23",
    "source": "Product Hunt",
    "discovered_at": "2026-02-25T02:57:44.139635+00:00",
    "categories": [
      "Developer Tools",
      "API",
      "Agents"
    ],
    "region": "Global"
  },
  {
    "name": "Siteline",
    "website": "https://siteline.ai/",
    "description": "Analytics tool focused on AI-agent and bot traffic, helping teams improve visibility in AI-driven discovery channels.",
    "why_matters": "Surfaced on Feb 23 Product Hunt with 512 upvotes and states 30% of web traffic is already bot/agent-driven, matching current SEO shifts.",
    "dark_horse_index": 4,
    "source_url": "https://www.producthunt.com/leaderboard/daily/2026/2/23",
    "source": "Product Hunt",
    "discovered_at": "2026-02-25T02:57:44.139635+00:00",
    "categories": [
      "Analytics",
      "AI Search"
    ],
    "region": "Global"
  },
  {
    "name": "Modelence App Builder",
    "website": "https://modelence.com/",
    "description": "AI app builder for shipping production apps with built-in auth, database primitives, and observability defaults.",
    "why_matters": "Ranked on Feb 24 Product Hunt with 352 upvotes and positions itself as production-ready by default, not prototype-only tooling.",
    "dark_horse_index": 4,
    "source_url": "https://www.producthunt.com/leaderboard/daily/2026/2/24",
    "source": "Product Hunt",
    "discovered_at": "2026-02-25T02:57:44.139635+00:00",
    "categories": [
      "Developer Tools",
      "App Builder"
    ],
    "region": "Global"
  },
  {
    "name": "Orchids 1.0",
    "website": "https://www.orchids.app/",
    "description": "AI app builder that supports multi-stack generation and lets users bring existing model subscriptions or API keys.",
    "why_matters": "Announced Feb 9 and remained hot on Feb 24 Product Hunt; claims 1M+ users and benchmark lead (76% App Bench), indicating rapid adoption.",
    "dark_horse_index": 3,
    "source_url": "https://www.orchids.app/blog/introducing-orchids-1-0",
    "source": "Product Hunt + Official Blog",
    "discovered_at": "2026-02-25T02:57:44.139635+00:00",
    "categories": [
      "App Builder",
      "Agents"
    ],
    "region": "Global"
  }
]